docuver/__init__.py
docuver/cli.py
docuver/completions.py
docuver/core.py
docuver/version.py
docuver-0.1.0.dist-info/licenses/LICENSE
docuver-0.1.0.dist-info/METADATA
docuver-0.1.0.dist-info/WHEEL
docuver-0.1.0.dist-info/entry_points.txt
docuver-0.1.0.dist-info/top_level.txt
docuver-0.1.0.dist-info/RECORD
