Metadata-Version: 2.4
Name: docuver
Version: 0.1.0
Summary: A meta tool for version control of Office documents (docx, xlsx, pptx, odt, ods, odp)
Home-page: https://github.com/jabezwinston/dcouver
Author: Jabez Winston C
Author-email: Jabez Winston C <jabezwinston@gmail.com>
License-Expression: MIT
Project-URL: Homepage, https://github.com/jabezwinston/dcouver
Project-URL: Bug Reports, https://github.com/jabezwinston/dcouver/issues
Project-URL: Source, https://github.com/jabezwinston/dcouver
Keywords: version-control,office,documents,docx,xlsx,odt,ods,odp,meta-tool,git
Classifier: Development Status :: 3 - Alpha
Classifier: Intended Audience :: Developers
Classifier: Intended Audience :: End Users/Desktop
Classifier: Topic :: Software Development :: Version Control
Classifier: Topic :: Office/Business :: Office Suites
Classifier: Programming Language :: Python :: 3
Classifier: Operating System :: OS Independent
Requires-Python: >=3.6
License-File: LICENSE
Provides-Extra: completions
Requires-Dist: argcomplete>=1.0; extra == "completions"
Dynamic: author
Dynamic: home-page
Dynamic: license-file
Dynamic: requires-python
